dosa/__init__.py
dosa/more.py
dosa/tests/__init__.py
dosa/tests/test_domain_actions.py
dosa/tests/test_domain_records.py
dosa/tests/test_droplet_actions.py
dosa/tests/test_firewall_actions.py
dosa/tests/test_image_actions.py
dosa/tests/test_key_actions.py
dosa-0.10.dist-info/LICENSE
dosa-0.10.dist-info/METADATA
dosa-0.10.dist-info/WHEEL
dosa-0.10.dist-info/top_level.txt
dosa-0.10.dist-info/RECORD
