Metadata-Version: 2.1
Name: dosa
Version: 0.10
Summary: Python wrapper for Digital Ocean API V2
Home-page: https://github.com/shon/dosa/
Author: Shekhar Tiwatne
Author-email: pythonic@gmail.com
License: http://www.opensource.org/licenses/mit-license.php
Platform: UNKNOWN
Classifier: Programming Language :: Python
Classifier: Programming Language :: Python :: 3
Requires-Dist: requests
